tests/__init__.py
tests/test_topsis.py
topsis/__init__.py
topsis/topsis.py
topsis_krishna-1.0.1.dist-info/licenses/LICENSE
topsis_krishna-1.0.1.dist-info/METADATA
topsis_krishna-1.0.1.dist-info/WHEEL
topsis_krishna-1.0.1.dist-info/entry_points.txt
topsis_krishna-1.0.1.dist-info/top_level.txt
topsis_krishna-1.0.1.dist-info/RECORD
