Metadata-Version: 2.4
Name: topsis-krishna
Version: 1.0.1
Summary: A Python implementation of the TOPSIS decision-making method
Home-page: https://github.com/yourusername/topsis-package
Author: Krishna Arora
Author-email: Krishna Arora <your.email@example.com>
License: MIT
Project-URL: Homepage, https://github.com/yourusername/topsis-package
Project-URL: Repository, https://github.com/yourusername/topsis-package
Project-URL: Documentation, https://github.com/yourusername/topsis-package#readme
Project-URL: Issues, https://github.com/yourusername/topsis-package/issues
Keywords: topsis,decision-making,multi-criteria,ranking,optimization
Classifier: Development Status :: 4 - Beta
Classifier: Intended Audience :: Science/Research
Classifier: Intended Audience :: Developers
Classifier: License :: OSI Approved :: MIT License
Classifier: Programming Language :: Python :: 3
Classifier: Programming Language :: Python :: 3.6
Classifier: Programming Language :: Python :: 3.7
Classifier: Programming Language :: Python :: 3.8
Classifier: Programming Language :: Python :: 3.9
Classifier: Programming Language :: Python :: 3.10
Classifier: Programming Language :: Python :: 3.11
Classifier: Operating System :: OS Independent
Classifier: Topic :: Scientific/Engineering :: Mathematics
Classifier: Topic :: Software Development :: Libraries :: Python Modules
Requires-Python: >=3.6
License-File: LICENSE
Requires-Dist: numpy>=1.19.0
Requires-Dist: pandas>=1.1.0
Provides-Extra: dev
Requires-Dist: pytest>=6.0; extra == "dev"
Requires-Dist: pytest-cov>=2.0; extra == "dev"
Requires-Dist: black>=21.0; extra == "dev"
Requires-Dist: flake8>=3.8; extra == "dev"
Dynamic: author
Dynamic: home-page
Dynamic: license-file
Dynamic: requires-python
